milvio/__init__.py
milvio/tools/__init__.py
milvio/tools/redis_tool/__init__.py
milvio/tools/redis_tool/redis_service.py
milvio-0.1.0.dist-info/licenses/LICENSE
milvio-0.1.0.dist-info/METADATA
milvio-0.1.0.dist-info/WHEEL
milvio-0.1.0.dist-info/top_level.txt
milvio-0.1.0.dist-info/RECORD
