Metadata-Version: 2.4
Name: milvio
Version: 0.1.0
Summary: Milvio Package and tools
Home-page: https://github.com/MilvioLua/python
Author: Milvio Lua
Author-email: Milvio Lua <developer@godigitalda.com>
License: MIT License
Project-URL: Homepage, https://github.com/MilvioLua/python
Classifier: Programming Language :: Python :: 3
Classifier: License :: OSI Approved :: MIT License
Classifier: Operating System :: OS Independent
Requires-Python: >=3.8
License-File: LICENSE
Requires-Dist: redis>=4.0.0
Dynamic: author
Dynamic: home-page
Dynamic: license-file
Dynamic: requires-python
